django_commands_suite/__init__.py
django_commands_suite/admin.py
django_commands_suite/apps.py
django_commands_suite/models.py
django_commands_suite/urls.py
django_commands_suite/utils.py
django_commands_suite/views.py
django_commands_suite/management/__init__.py
django_commands_suite/management/commands/__init__.py
django_commands_suite/management/commands/backup_db.py
django_commands_suite/management/commands/backup_media.py
django_commands_suite/management/commands/dcs_help.py
django_commands_suite/management/commands/dummy_data.py
django_commands_suite/management/commands/export_data.py
django_commands_suite/management/commands/flush_sessions.py
django_commands_suite/management/commands/gen_key.py
django_commands_suite/management/commands/quick_superuser.py
django_commands_suite/templates/django_commands_suite/webterminal.html
django_commands_suite-0.2.5.dist-info/licenses/LICENSE
django_commands_suite-0.2.5.dist-info/METADATA
django_commands_suite-0.2.5.dist-info/WHEEL
django_commands_suite-0.2.5.dist-info/top_level.txt
django_commands_suite-0.2.5.dist-info/RECORD
