Metadata-Version: 2.4
Name: django-commands-suite
Version: 0.2.5
Summary: A powerful suite of management commands for Django projects with integrated logging support
Author-email: Mohammed taha <net@khamedspace.com>
License: MIT
Project-URL: homepage, https://github.com/khamedtaha/django-commands-suite
Project-URL: repository, https://github.com/khamedtaha/django-commands-suite
Keywords: django,commands,management,suite,log
License-File: LICENSE
Requires-Dist: Django>=5.0
Requires-Dist: Faker>=18.0.0
Dynamic: license-file
